nsip_mcp/__init__.py
nsip_mcp/cache.py
nsip_mcp/cli.py
nsip_mcp/context.py
nsip_mcp/errors.py
nsip_mcp/mcp_tools.py
nsip_mcp/metrics.py
nsip_mcp/server.py
nsip_mcp/tools.py
nsip_mcp/transport.py
nsip_mcp/knowledge_base/__init__.py
nsip_mcp/knowledge_base/loader.py
nsip_mcp/knowledge_base/data/calendar_templates.yaml
nsip_mcp/knowledge_base/data/diseases.yaml
nsip_mcp/knowledge_base/data/economics.yaml
nsip_mcp/knowledge_base/data/heritabilities.yaml
nsip_mcp/knowledge_base/data/nutrition.yaml
nsip_mcp/knowledge_base/data/regions.yaml
nsip_mcp/knowledge_base/data/selection_indexes.yaml
nsip_mcp/knowledge_base/data/trait_glossary.yaml
nsip_mcp/knowledge_base/schema/__init__.py
nsip_mcp/knowledge_base/schema/kb_schema.py
nsip_mcp/prompts/__init__.py
nsip_mcp/prompts/interview_prompts.py
nsip_mcp/prompts/shepherd_prompts.py
nsip_mcp/prompts/skill_prompts.py
nsip_mcp/resources/__init__.py
nsip_mcp/resources/animal_resources.py
nsip_mcp/resources/breeding_resources.py
nsip_mcp/resources/flock_resources.py
nsip_mcp/resources/static_resources.py
nsip_mcp/shepherd/__init__.py
nsip_mcp/shepherd/agent.py
nsip_mcp/shepherd/persona.py
nsip_mcp/shepherd/regions.py
nsip_mcp/shepherd/domains/__init__.py
nsip_mcp/shepherd/domains/base.py
nsip_mcp/shepherd/domains/breeding.py
nsip_mcp/shepherd/domains/calendar.py
nsip_mcp/shepherd/domains/economics.py
nsip_mcp/shepherd/domains/health.py
nsip_mcp_server-1.4.7.dist-info/METADATA
nsip_mcp_server-1.4.7.dist-info/WHEEL
nsip_mcp_server-1.4.7.dist-info/entry_points.txt
nsip_mcp_server-1.4.7.dist-info/RECORD
