Metadata-Version: 2.4
Name: nsip-mcp-server
Version: 1.4.7
Summary: MCP server for NSIP sheep breeding data - Context-efficient API-to-MCP gateway
Project-URL: Homepage, https://github.com/epicpast/nsip-api-client
Project-URL: Documentation, https://github.com/epicpast/nsip-api-client#readme
Project-URL: Repository, https://github.com/epicpast/nsip-api-client.git
Project-URL: Bug Tracker, https://github.com/epicpast/nsip-api-client/issues
Project-URL: Releases, https://github.com/epicpast/nsip-api-client/releases
Author-email: Robert Allen <bob@epicpastures.com>
License: MIT
Keywords: breeding,llm,mcp,model-context-protocol,nsip,sheep
Classifier: Development Status :: 4 - Beta
Classifier: Intended Audience :: Developers
Classifier: Intended Audience :: Science/Research
Classifier: License :: OSI Approved :: MIT License
Classifier: Programming Language :: Python :: 3
Classifier: Programming Language :: Python :: 3.12
Classifier: Programming Language :: Python :: 3.13
Classifier: Topic :: Scientific/Engineering
Classifier: Topic :: Software Development :: Libraries :: Python Modules
Requires-Python: >=3.12
Requires-Dist: fastmcp>=2.0
Requires-Dist: nsip-client<2.0.0,>=1.4.7
Requires-Dist: tiktoken>=0.8.0
